Metadata-Version: 2.1
Name: GriffinX
Version: 0.8
Summary: GriffinX is a middleware package for real time event detection
Home-page: https://github.com/kiran-collab/Griffin-Drone-Car-Collaboration
Author: Percom@UMD
Author-email: kirandav@umich.edu
License: MIT
Classifier: Programming Language :: Python :: 3
Classifier: License :: OSI Approved :: MIT License
License-File: LICENSE.txt
Requires-Dist: torch
Requires-Dist: numpy
Requires-Dist: ultralytics
Requires-Dist: opencv-python>=4.9.0.80
Requires-Dist: pillow>=10.2.0
